sgtl/__init__.py
sgtl/algorithms.py
sgtl/clustering.py
sgtl/graph.py
sgtl/random.py
sgtl/spectrum.py
sgtl-0.5.0.dist-info/LICENSE
sgtl-0.5.0.dist-info/METADATA
sgtl-0.5.0.dist-info/WHEEL
sgtl-0.5.0.dist-info/top_level.txt
sgtl-0.5.0.dist-info/RECORD
