Metadata-Version: 2.1
Name: sgtl
Version: 0.5.0
Summary: SGTL - Spectral Graph Theory Library
Home-page: UNKNOWN
Author: Peter Macgregor
Author-email: <macgregor.pr@gmail.com>
License: UNKNOWN
Keywords: python,spectral,graph,algorithms,clustering,cheeger
Platform: UNKNOWN
Classifier: Development Status :: 3 - Alpha
Classifier: Intended Audience :: Education
Classifier: Programming Language :: Python :: 3
Classifier: Operating System :: MacOS :: MacOS X
Classifier: Operating System :: Microsoft :: Windows
Classifier: Operating System :: POSIX :: Linux
License-File: LICENSE
Requires-Dist: matplotlib
Requires-Dist: networkx (<3.0)
Requires-Dist: numpy
Requires-Dist: pandas
Requires-Dist: scikit-learn
Requires-Dist: scipy
